usagebyuser.py
grake-0.0.1.dist-info/WHEEL
grake-0.0.1.dist-info/METADATA
grake-0.0.1.dist-info/RECORD
