Metadata-Version: 2.1
Name: grake
Version: 0.0.1
Summary: tool for managing storage on the UM GReat lAKE cluster
License: MIT
Author-email: Andrew Robbins <robbiand@med.umich.edu>
Requires-Python: >=3.10
Requires-Dist: globus-sdk>=3.10.1
Requires-Dist: ipython>=8.4.0
Requires-Dist: numpy>=1.23.2
Requires-Dist: pandas>=1.4.3
